simplehttp/__init__.py
simplehttp/error.py
simplehttp/http_client.py
simplehttp/utils.py
ethanypc_simplerequest-1.0.3.dist-info/METADATA
ethanypc_simplerequest-1.0.3.dist-info/WHEEL
ethanypc_simplerequest-1.0.3.dist-info/top_level.txt
ethanypc_simplerequest-1.0.3.dist-info/RECORD
