Metadata-Version: 2.1
Name: ethanypc-simplerequest
Version: 1.0.3
Summary: Wrapper around http.client
Home-page: https://github.com/EthanChenYen-Peng/simplerequest
Author: Ethan
Author-email: ypcethan@gmail.com
License: MIT
Platform: UNKNOWN
Classifier: License :: OSI Approved :: MIT License
Classifier: Programming Language :: Python :: 3
Classifier: Operating System :: OS Independent
